{"Country":"United Kingdom","InvoiceNo":"538180","TotalQuantity":178,"InvoiceValue":369.1,"InvoiceValueExpr":369.1}
{"Country":"United Kingdom","InvoiceNo":"538535","TotalQuantity":61,"InvoiceValue":127.0,"InvoiceValueExpr":127.0}
{"Country":"Australia","InvoiceNo":"C538723","TotalQuantity":-13,"InvoiceValue":-27.75,"InvoiceValueExpr":-27.75}
{"Country":"United Kingdom","InvoiceNo":"538810","TotalQuantity":38,"InvoiceValue":140.4,"InvoiceValueExpr":140.4}
{"Country":"United Kingdom","InvoiceNo":"539472","TotalQuantity":20,"InvoiceValue":31.62,"InvoiceValueExpr":31.62}
{"Country":"United Kingdom","InvoiceNo":"C539632","TotalQuantity":-96,"InvoiceValue":-162.24,"InvoiceValueExpr":-162.24}
{"Country":"United Kingdom","InvoiceNo":"539998","TotalQuantity":2,"InvoiceValue":0.0,"InvoiceValueExpr":0.0}
{"Country":"United Kingdom","InvoiceNo":"540159","TotalQuantity":192,"InvoiceValue":72.0,"InvoiceValueExpr":72.0}
{"Country":"United Kingdom","InvoiceNo":"540276","TotalQuantity":669,"InvoiceValue":1520.11,"InvoiceValueExpr":1520.11}
{"Country":"United Kingdom","InvoiceNo":"540533","TotalQuantity":67,"InvoiceValue":141.05,"InvoiceValueExpr":141.05}
{"Country":"United Kingdom","InvoiceNo":"540836","TotalQuantity":15,"InvoiceValue":12.75,"InvoiceValueExpr":12.75}
{"Country":"United Kingdom","InvoiceNo":"C541257","TotalQuantity":-1,"InvoiceValue":-4.95,"InvoiceValueExpr":-4.95}
{"Country":"United Kingdom","InvoiceNo":"541788","TotalQuantity":160,"InvoiceValue":307.6,"InvoiceValueExpr":307.6}
{"Country":"United Kingdom","InvoiceNo":"C542403","TotalQuantity":-4,"InvoiceValue":-31.8,"InvoiceValueExpr":-31.8}
{"Country":"United Kingdom","InvoiceNo":"542536","TotalQuantity":332,"InvoiceValue":1264.34,"InvoiceValueExpr":1264.34}
{"Country":"United Kingdom","InvoiceNo":"C542753","TotalQuantity":-1,"InvoiceValue":-4.95,"InvoiceValueExpr":-4.95}
{"Country":"United Kingdom","InvoiceNo":"543325","TotalQuantity":66,"InvoiceValue":110.7,"InvoiceValueExpr":110.7}
{"Country":"United Kingdom","InvoiceNo":"543656","TotalQuantity":-44,"InvoiceValue":0.0,"InvoiceValueExpr":0.0}
{"Country":"United Kingdom","InvoiceNo":"544446","TotalQuantity":100,"InvoiceValue":42.0,"InvoiceValueExpr":42.0}
{"Country":"Belgium","InvoiceNo":"C544902","TotalQuantity":-2,"InvoiceValue":-4.9,"InvoiceValueExpr":-4.9}
{"Country":"United Kingdom","InvoiceNo":"C545068","TotalQuantity":-11,"InvoiceValue":-32.45,"InvoiceValueExpr":-32.45}
{"Country":"United Kingdom","InvoiceNo":"546381","TotalQuantity":9,"InvoiceValue":19.74,"InvoiceValueExpr":19.74}
{"Country":"United Kingdom","InvoiceNo":"546538","TotalQuantity":359,"InvoiceValue":582.35,"InvoiceValueExpr":582.35}
{"Country":"United Kingdom","InvoiceNo":"546658","TotalQuantity":331,"InvoiceValue":501.25,"InvoiceValueExpr":501.25}
{"Country":"Germany","InvoiceNo":"546920","TotalQuantity":296,"InvoiceValue":845.32,"InvoiceValueExpr":845.32}
{"Country":"United Kingdom","InvoiceNo":"547347","TotalQuantity":-6,"InvoiceValue":0.0,"InvoiceValueExpr":0.0}
{"Country":"United Kingdom","InvoiceNo":"547860","TotalQuantity":382,"InvoiceValue":549.68,"InvoiceValueExpr":549.68}
{"Country":"France","InvoiceNo":"547863","TotalQuantity":61,"InvoiceValue":164.05,"InvoiceValueExpr":164.05}
{"Country":"EIRE","InvoiceNo":"547993","TotalQuantity":334,"InvoiceValue":523.15,"InvoiceValueExpr":523.15}
{"Country":"United Kingdom","InvoiceNo":"C548717","TotalQuantity":-24,"InvoiceValue":-20.4,"InvoiceValueExpr":-20.4}
{"Country":"United Kingdom","InvoiceNo":"549281","TotalQuantity":330,"InvoiceValue":571.3,"InvoiceValueExpr":571.3}
{"Country":"United Kingdom","InvoiceNo":"549293","TotalQuantity":48,"InvoiceValue":119.35,"InvoiceValueExpr":119.35}
{"Country":"United Kingdom","InvoiceNo":"549982","TotalQuantity":323,"InvoiceValue":505.57,"InvoiceValueExpr":505.57}
{"Country":"United Kingdom","InvoiceNo":"550471","TotalQuantity":553,"InvoiceValue":1599.85,"InvoiceValueExpr":1599.85}
{"Country":"United Kingdom","InvoiceNo":"C550966","TotalQuantity":-1,"InvoiceValue":-7.95,"InvoiceValueExpr":-7.95}
{"Country":"United Kingdom","InvoiceNo":"551001","TotalQuantity":190,"InvoiceValue":564.5,"InvoiceValueExpr":564.5}
{"Country":"United Kingdom","InvoiceNo":"551012","TotalQuantity":555,"InvoiceValue":3036.22,"InvoiceValueExpr":3036.22}
{"Country":"United Kingdom","InvoiceNo":"551171","TotalQuantity":157,"InvoiceValue":282.7,"InvoiceValueExpr":282.7}
{"Country":"United Kingdom","InvoiceNo":"552293","TotalQuantity":110,"InvoiceValue":173.12,"InvoiceValueExpr":173.12}
{"Country":"United Kingdom","InvoiceNo":"552676","TotalQuantity":106,"InvoiceValue":864.26,"InvoiceValueExpr":864.26}
{"Country":"United Kingdom","InvoiceNo":"553006","TotalQuantity":393,"InvoiceValue":560.35,"InvoiceValueExpr":560.35}
{"Country":"United Kingdom","InvoiceNo":"553204","TotalQuantity":35,"InvoiceValue":77.75,"InvoiceValueExpr":77.75}
{"Country":"United Kingdom","InvoiceNo":"C553914","TotalQuantity":-7,"InvoiceValue":-50.45,"InvoiceValueExpr":-50.45}
{"Country":"United Kingdom","InvoiceNo":"554676","TotalQuantity":-31,"InvoiceValue":0.0,"InvoiceValueExpr":0.0}
{"Country":"United Kingdom","InvoiceNo":"C554849","TotalQuantity":-7,"InvoiceValue":-37.48,"InvoiceValueExpr":-37.48}
{"Country":"United Kingdom","InvoiceNo":"554929","TotalQuantity":313,"InvoiceValue":366.87,"InvoiceValueExpr":366.87}
{"Country":"United Kingdom","InvoiceNo":"555112","TotalQuantity":201,"InvoiceValue":314.47,"InvoiceValueExpr":314.47}
{"Country":"United Kingdom","InvoiceNo":"555157","TotalQuantity":63,"InvoiceValue":287.45,"InvoiceValueExpr":287.45}
{"Country":"United Kingdom","InvoiceNo":"555389","TotalQuantity":33,"InvoiceValue":233.75,"InvoiceValueExpr":233.75}
{"Country":"United Kingdom","InvoiceNo":"555733","TotalQuantity":304,"InvoiceValue":402.08,"InvoiceValueExpr":402.08}
{"Country":"United Kingdom","InvoiceNo":"556090","TotalQuantity":59,"InvoiceValue":200.13,"InvoiceValueExpr":200.13}
{"Country":"United Kingdom","InvoiceNo":"556238","TotalQuantity":109,"InvoiceValue":378.7,"InvoiceValueExpr":378.7}
{"Country":"United Kingdom","InvoiceNo":"556322","TotalQuantity":-204,"InvoiceValue":0.0,"InvoiceValueExpr":0.0}
{"Country":"United Kingdom","InvoiceNo":"556944","TotalQuantity":-29,"InvoiceValue":0.0,"InvoiceValueExpr":0.0}
{"Country":"United Kingdom","InvoiceNo":"C557709","TotalQuantity":-2,"InvoiceValue":-9.9,"InvoiceValueExpr":-9.9}
{"Country":"Germany","InvoiceNo":"558881","TotalQuantity":863,"InvoiceValue":998.42,"InvoiceValueExpr":998.42}
{"Country":"Spain","InvoiceNo":"559187","TotalQuantity":11,"InvoiceValue":46.75,"InvoiceValueExpr":46.75}
{"Country":"United Kingdom","InvoiceNo":"559944","TotalQuantity":78,"InvoiceValue":596.7,"InvoiceValueExpr":596.7}
{"Country":"United Kingdom","InvoiceNo":"560182","TotalQuantity":203,"InvoiceValue":254.35,"InvoiceValueExpr":254.35}
{"Country":"United Kingdom","InvoiceNo":"560209","TotalQuantity":630,"InvoiceValue":1246.32,"InvoiceValueExpr":1246.32}
{"Country":"United Kingdom","InvoiceNo":"561692","TotalQuantity":30,"InvoiceValue":115.8,"InvoiceValueExpr":115.8}
{"Country":"United Kingdom","InvoiceNo":"561895","TotalQuantity":1,"InvoiceValue":1.25,"InvoiceValueExpr":1.25}
{"Country":"United Kingdom","InvoiceNo":"562433","TotalQuantity":621,"InvoiceValue":1016.04,"InvoiceValueExpr":1016.04}
{"Country":"United Kingdom","InvoiceNo":"562885","TotalQuantity":51,"InvoiceValue":65.25,"InvoiceValueExpr":65.25}
{"Country":"United Kingdom","InvoiceNo":"539825","TotalQuantity":3,"InvoiceValue":9.35,"InvoiceValueExpr":9.35}
{"Country":"United Kingdom","InvoiceNo":"554982","TotalQuantity":271,"InvoiceValue":1155.6,"InvoiceValueExpr":1155.6}
{"Country":"United Kingdom","InvoiceNo":"560882","TotalQuantity":148,"InvoiceValue":312.59,"InvoiceValueExpr":312.59}
{"Country":"United Kingdom","InvoiceNo":"C562910","TotalQuantity":-16,"InvoiceValue":-4.64,"InvoiceValueExpr":-4.64}
{"Country":"United Kingdom","InvoiceNo":"563691","TotalQuantity":345,"InvoiceValue":431.11,"InvoiceValueExpr":431.11}
{"Country":"Germany","InvoiceNo":"C564104","TotalQuantity":-13,"InvoiceValue":-38.65,"InvoiceValueExpr":-38.65}
{"Country":"United Kingdom","InvoiceNo":"565803","TotalQuantity":454,"InvoiceValue":871.25,"InvoiceValueExpr":871.25}
{"Country":"United Kingdom","InvoiceNo":"566121","TotalQuantity":-682,"InvoiceValue":0.0,"InvoiceValueExpr":0.0}
{"Country":"United Kingdom","InvoiceNo":"566254","TotalQuantity":90,"InvoiceValue":384.9,"InvoiceValueExpr":384.9}
{"Country":"Germany","InvoiceNo":"567578","TotalQuantity":432,"InvoiceValue":460.63,"InvoiceValueExpr":460.63}
{"Country":"United Kingdom","InvoiceNo":"567623","TotalQuantity":114,"InvoiceValue":507.84,"InvoiceValueExpr":507.84}
{"Country":"United Kingdom","InvoiceNo":"567683","TotalQuantity":150,"InvoiceValue":269.16,"InvoiceValueExpr":269.16}
{"Country":"United Kingdom","InvoiceNo":"C567946","TotalQuantity":-3,"InvoiceValue":-7.39,"InvoiceValueExpr":-7.39}
{"Country":"United Kingdom","InvoiceNo":"568316","TotalQuantity":132,"InvoiceValue":265.14,"InvoiceValueExpr":265.14}
{"Country":"United Kingdom","InvoiceNo":"C569112","TotalQuantity":-12,"InvoiceValue":-33.96,"InvoiceValueExpr":-33.96}
{"Country":"United Kingdom","InvoiceNo":"569546","TotalQuantity":64,"InvoiceValue":135.31,"InvoiceValueExpr":135.31}
{"Country":"United Kingdom","InvoiceNo":"569641","TotalQuantity":119,"InvoiceValue":196.65,"InvoiceValueExpr":196.65}
{"Country":"Australia","InvoiceNo":"569723","TotalQuantity":28,"InvoiceValue":89.8,"InvoiceValueExpr":89.8}
{"Country":"United Kingdom","InvoiceNo":"C569996","TotalQuantity":-51,"InvoiceValue":-76.71,"InvoiceValueExpr":-76.71}
{"Country":"United Kingdom","InvoiceNo":"570180","TotalQuantity":500,"InvoiceValue":898.14,"InvoiceValueExpr":898.14}
{"Country":"United Kingdom","InvoiceNo":"C570658","TotalQuantity":-12,"InvoiceValue":-15.0,"InvoiceValueExpr":-15.0}
{"Country":"United Kingdom","InvoiceNo":"570852","TotalQuantity":160,"InvoiceValue":333.6,"InvoiceValueExpr":333.6}
{"Country":"United Kingdom","InvoiceNo":"571265","TotalQuantity":125,"InvoiceValue":197.41,"InvoiceValueExpr":197.41}
{"Country":"United Kingdom","InvoiceNo":"571283","TotalQuantity":375,"InvoiceValue":610.89,"InvoiceValueExpr":610.89}
{"Country":"United Kingdom","InvoiceNo":"571566","TotalQuantity":359,"InvoiceValue":396.97,"InvoiceValueExpr":396.97}
{"Country":"EIRE","InvoiceNo":"C572120","TotalQuantity":-21,"InvoiceValue":-54.9,"InvoiceValueExpr":-54.9}
{"Country":"United Kingdom","InvoiceNo":"572139","TotalQuantity":20,"InvoiceValue":54.6,"InvoiceValueExpr":54.6}
{"Country":"United Kingdom","InvoiceNo":"572210","TotalQuantity":52,"InvoiceValue":124.8,"InvoiceValueExpr":124.8}
{"Country":"United Kingdom","InvoiceNo":"572232","TotalQuantity":160,"InvoiceValue":303.58,"InvoiceValueExpr":303.58}
{"Country":"United Kingdom","InvoiceNo":"572314","TotalQuantity":302,"InvoiceValue":248.61,"InvoiceValueExpr":248.61}
{"Country":"Belgium","InvoiceNo":"572887","TotalQuantity":213,"InvoiceValue":786.95,"InvoiceValueExpr":786.95}
{"Country":"United Kingdom","InvoiceNo":"573166","TotalQuantity":296,"InvoiceValue":706.36,"InvoiceValueExpr":706.36}
{"Country":"United Kingdom","InvoiceNo":"573276","TotalQuantity":356,"InvoiceValue":544.1,"InvoiceValueExpr":544.1}
{"Country":"United Kingdom","InvoiceNo":"574530","TotalQuantity":157,"InvoiceValue":194.88,"InvoiceValueExpr":194.88}
{"Country":"United Kingdom","InvoiceNo":"575222","TotalQuantity":146,"InvoiceValue":410.06,"InvoiceValueExpr":410.06}
{"Country":"United Kingdom","InvoiceNo":"575330","TotalQuantity":268,"InvoiceValue":309.08,"InvoiceValueExpr":309.08}
{"Country":"United Kingdom","InvoiceNo":"575900","TotalQuantity":7,"InvoiceValue":22.79,"InvoiceValueExpr":22.79}
{"Country":"United Kingdom","InvoiceNo":"576067","TotalQuantity":187,"InvoiceValue":319.06,"InvoiceValueExpr":319.06}
{"Country":"United Kingdom","InvoiceNo":"576668","TotalQuantity":96,"InvoiceValue":363.2,"InvoiceValueExpr":363.2}
{"Country":"France","InvoiceNo":"576672","TotalQuantity":662,"InvoiceValue":1497.52,"InvoiceValueExpr":1497.52}
{"Country":"United Kingdom","InvoiceNo":"577025","TotalQuantity":174,"InvoiceValue":363.62,"InvoiceValueExpr":363.62}
{"Country":"Belgium","InvoiceNo":"577551","TotalQuantity":125,"InvoiceValue":265.83,"InvoiceValueExpr":265.83}
{"Country":"United Kingdom","InvoiceNo":"C577781","TotalQuantity":-3,"InvoiceValue":-17.85,"InvoiceValueExpr":-17.85}
{"Country":"United Kingdom","InvoiceNo":"577893","TotalQuantity":159,"InvoiceValue":279.37,"InvoiceValueExpr":279.37}
{"Country":"United Kingdom","InvoiceNo":"578681","TotalQuantity":130,"InvoiceValue":302.34,"InvoiceValueExpr":302.34}
{"Country":"United Kingdom","InvoiceNo":"579291","TotalQuantity":955,"InvoiceValue":4584.66,"InvoiceValueExpr":4584.66}
{"Country":"United Kingdom","InvoiceNo":"579406","TotalQuantity":54,"InvoiceValue":304.9,"InvoiceValueExpr":304.9}
{"Country":"United Kingdom","InvoiceNo":"579954","TotalQuantity":705,"InvoiceValue":498.44,"InvoiceValueExpr":498.44}
{"Country":"United Kingdom","InvoiceNo":"579980","TotalQuantity":76,"InvoiceValue":136.85,"InvoiceValueExpr":136.85}
{"Country":"United Kingdom","InvoiceNo":"580533","TotalQuantity":18,"InvoiceValue":96.3,"InvoiceValueExpr":96.3}
{"Country":"United Kingdom","InvoiceNo":"580552","TotalQuantity":94,"InvoiceValue":194.98,"InvoiceValueExpr":194.98}
{"Country":"United Kingdom","InvoiceNo":"581514","TotalQuantity":405,"InvoiceValue":200.99,"InvoiceValueExpr":200.99}
{"Country":"Germany","InvoiceNo":"C577693","TotalQuantity":-3,"InvoiceValue":-16.85,"InvoiceValueExpr":-16.85}
