{"Country":"United Kingdom","InvoiceNo":"C536822","TotalQuantity":-3,"InvoiceValue":-37.65,"InvoiceValueExpr":-37.65}
{"Country":"United Kingdom","InvoiceNo":"536849","TotalQuantity":106,"InvoiceValue":397.5,"InvoiceValueExpr":397.5}
{"Country":"United Kingdom","InvoiceNo":"537223","TotalQuantity":46,"InvoiceValue":164.7,"InvoiceValueExpr":164.7}
{"Country":"United Kingdom","InvoiceNo":"537509","TotalQuantity":288,"InvoiceValue":532.8,"InvoiceValueExpr":532.8}
{"Country":"United Kingdom","InvoiceNo":"C537651","TotalQuantity":-1,"InvoiceValue":-13541.33,"InvoiceValueExpr":-13541.33}
{"Country":"United Kingdom","InvoiceNo":"537653","TotalQuantity":84,"InvoiceValue":268.73,"InvoiceValueExpr":268.73}
{"Country":"United Kingdom","InvoiceNo":"C538100","TotalQuantity":-12,"InvoiceValue":-30.6,"InvoiceValueExpr":-30.6}
{"Country":"United Kingdom","InvoiceNo":"538666","TotalQuantity":7,"InvoiceValue":12.85,"InvoiceValueExpr":12.85}
{"Country":"United Kingdom","InvoiceNo":"C538699","TotalQuantity":-4,"InvoiceValue":-31.8,"InvoiceValueExpr":-31.8}
{"Country":"United Kingdom","InvoiceNo":"539442","TotalQuantity":127,"InvoiceValue":311.15,"InvoiceValueExpr":311.15}
{"Country":"United Kingdom","InvoiceNo":"540258","TotalQuantity":212,"InvoiceValue":682.8,"InvoiceValueExpr":682.8}
{"Country":"France","InvoiceNo":"540642","TotalQuantity":635,"InvoiceValue":1238.06,"InvoiceValueExpr":1238.06}
{"Country":"United Kingdom","InvoiceNo":"540990","TotalQuantity":143,"InvoiceValue":258.41,"InvoiceValueExpr":258.41}
{"Country":"United Kingdom","InvoiceNo":"541236","TotalQuantity":1,"InvoiceValue":3.35,"InvoiceValueExpr":3.35}
{"Country":"United Kingdom","InvoiceNo":"542382","TotalQuantity":83,"InvoiceValue":204.77,"InvoiceValueExpr":204.77}
{"Country":"United Kingdom","InvoiceNo":"542612","TotalQuantity":82,"InvoiceValue":165.9,"InvoiceValueExpr":165.9}
{"Country":"Germany","InvoiceNo":"542626","TotalQuantity":182,"InvoiceValue":279.3,"InvoiceValueExpr":279.3}
{"Country":"United Kingdom","InvoiceNo":"542785","TotalQuantity":706,"InvoiceValue":1025.34,"InvoiceValueExpr":1025.34}
{"Country":"United Kingdom","InvoiceNo":"542928","TotalQuantity":426,"InvoiceValue":505.98,"InvoiceValueExpr":505.98}
{"Country":"United Kingdom","InvoiceNo":"543461","TotalQuantity":68,"InvoiceValue":498.96,"InvoiceValueExpr":498.96}
{"Country":"United Kingdom","InvoiceNo":"543552","TotalQuantity":-10,"InvoiceValue":0.0,"InvoiceValueExpr":0.0}
{"Country":"United Kingdom","InvoiceNo":"543649","TotalQuantity":84,"InvoiceValue":610.2,"InvoiceValueExpr":610.2}
{"Country":"United Kingdom","InvoiceNo":"C543744","TotalQuantity":-19,"InvoiceValue":-62.13,"InvoiceValueExpr":-62.13}
{"Country":"United Kingdom","InvoiceNo":"544058","TotalQuantity":76,"InvoiceValue":230.15,"InvoiceValueExpr":230.15}
{"Country":"United Kingdom","InvoiceNo":"544065","TotalQuantity":104,"InvoiceValue":262.44,"InvoiceValueExpr":262.44}
{"Country":"United Kingdom","InvoiceNo":"544167","TotalQuantity":134,"InvoiceValue":506.02,"InvoiceValueExpr":506.02}
{"Country":"United Kingdom","InvoiceNo":"544686","TotalQuantity":4,"InvoiceValue":7.8,"InvoiceValueExpr":7.8}
{"Country":"United Kingdom","InvoiceNo":"544919","TotalQuantity":98,"InvoiceValue":147.3,"InvoiceValueExpr":147.3}
{"Country":"United Kingdom","InvoiceNo":"544943","TotalQuantity":358,"InvoiceValue":929.22,"InvoiceValueExpr":929.22}
{"Country":"France","InvoiceNo":"545180","TotalQuantity":73,"InvoiceValue":200.72,"InvoiceValueExpr":200.72}
{"Country":"United Kingdom","InvoiceNo":"545341","TotalQuantity":150,"InvoiceValue":1642.5,"InvoiceValueExpr":1642.5}
{"Country":"United Kingdom","InvoiceNo":"545430","TotalQuantity":82,"InvoiceValue":306.7,"InvoiceValueExpr":306.7}
{"Country":"United Kingdom","InvoiceNo":"545648","TotalQuantity":60,"InvoiceValue":96.8,"InvoiceValueExpr":96.8}
{"Country":"United Kingdom","InvoiceNo":"545905","TotalQuantity":196,"InvoiceValue":197.0,"InvoiceValueExpr":197.0}
{"Country":"United Kingdom","InvoiceNo":"546525","TotalQuantity":312,"InvoiceValue":619.6,"InvoiceValueExpr":619.6}
{"Country":"United Kingdom","InvoiceNo":"547038","TotalQuantity":66,"InvoiceValue":211.5,"InvoiceValueExpr":211.5}
{"Country":"United Kingdom","InvoiceNo":"547839","TotalQuantity":280,"InvoiceValue":649.78,"InvoiceValueExpr":649.78}
{"Country":"United Kingdom","InvoiceNo":"547938","TotalQuantity":244,"InvoiceValue":433.9,"InvoiceValueExpr":433.9}
{"Country":"Germany","InvoiceNo":"548412","TotalQuantity":49,"InvoiceValue":111.0,"InvoiceValueExpr":111.0}
{"Country":"United Kingdom","InvoiceNo":"548907","TotalQuantity":22,"InvoiceValue":505.0,"InvoiceValueExpr":505.0}
{"Country":"United Kingdom","InvoiceNo":"549514","TotalQuantity":-3,"InvoiceValue":0.0,"InvoiceValueExpr":0.0}
{"Country":"United Kingdom","InvoiceNo":"550121","TotalQuantity":68,"InvoiceValue":147.6,"InvoiceValueExpr":147.6}
{"Country":"United Kingdom","InvoiceNo":"550183","TotalQuantity":800,"InvoiceValue":1266.23,"InvoiceValueExpr":1266.23}
{"Country":"United Kingdom","InvoiceNo":"551579","TotalQuantity":-5,"InvoiceValue":0.0,"InvoiceValueExpr":0.0}
{"Country":"United Kingdom","InvoiceNo":"551582","TotalQuantity":-5,"InvoiceValue":0.0,"InvoiceValueExpr":0.0}
{"Country":"United Kingdom","InvoiceNo":"551688","TotalQuantity":179,"InvoiceValue":299.81,"InvoiceValueExpr":299.81}
{"Country":"United Kingdom","InvoiceNo":"C552021","TotalQuantity":-51,"InvoiceValue":-36.72,"InvoiceValueExpr":-36.72}
{"Country":"United Kingdom","InvoiceNo":"552036","TotalQuantity":81,"InvoiceValue":211.15,"InvoiceValueExpr":211.15}
{"Country":"United Kingdom","InvoiceNo":"552452","TotalQuantity":108,"InvoiceValue":148.08,"InvoiceValueExpr":148.08}
{"Country":"United Kingdom","InvoiceNo":"552572","TotalQuantity":1558,"InvoiceValue":2944.7,"InvoiceValueExpr":2944.7}
{"Country":"United Kingdom","InvoiceNo":"C552849","TotalQuantity":-21,"InvoiceValue":-61.95,"InvoiceValueExpr":-61.95}
{"Country":"Sweden","InvoiceNo":"552957","TotalQuantity":2794,"InvoiceValue":2557.88,"InvoiceValueExpr":2557.88}
{"Country":"United Kingdom","InvoiceNo":"553225","TotalQuantity":96,"InvoiceValue":283.32,"InvoiceValueExpr":283.32}
{"Country":"United Kingdom","InvoiceNo":"553351","TotalQuantity":176,"InvoiceValue":311.7,"InvoiceValueExpr":311.7}
{"Country":"United Kingdom","InvoiceNo":"553423","TotalQuantity":90,"InvoiceValue":187.42,"InvoiceValueExpr":187.42}
{"Country":"United Kingdom","InvoiceNo":"553671","TotalQuantity":322,"InvoiceValue":527.8,"InvoiceValueExpr":527.8}
{"Country":"United Kingdom","InvoiceNo":"553681","TotalQuantity":57,"InvoiceValue":152.17,"InvoiceValueExpr":152.17}
{"Country":"United Kingdom","InvoiceNo":"553719","TotalQuantity":1,"InvoiceValue":0.0,"InvoiceValueExpr":0.0}
{"Country":"United Kingdom","InvoiceNo":"553755","TotalQuantity":144,"InvoiceValue":367.2,"InvoiceValueExpr":367.2}
{"Country":"United Kingdom","InvoiceNo":"553852","TotalQuantity":361,"InvoiceValue":448.83,"InvoiceValueExpr":448.83}
{"Country":"United Kingdom","InvoiceNo":"554060","TotalQuantity":200,"InvoiceValue":380.0,"InvoiceValueExpr":380.0}
{"Country":"United Kingdom","InvoiceNo":"554265","TotalQuantity":15,"InvoiceValue":33.03,"InvoiceValueExpr":33.03}
{"Country":"United Kingdom","InvoiceNo":"554675","TotalQuantity":-33,"InvoiceValue":0.0,"InvoiceValueExpr":0.0}
{"Country":"France","InvoiceNo":"C555100","TotalQuantity":-1,"InvoiceValue":-16.95,"InvoiceValueExpr":-16.95}
{"Country":"United Kingdom","InvoiceNo":"556051","TotalQuantity":49,"InvoiceValue":180.04,"InvoiceValueExpr":180.04}
{"Country":"United Kingdom","InvoiceNo":"C556101","TotalQuantity":-1,"InvoiceValue":-4.15,"InvoiceValueExpr":-4.15}
{"Country":"United Kingdom","InvoiceNo":"556197","TotalQuantity":114,"InvoiceValue":202.38,"InvoiceValueExpr":202.38}
{"Country":"United Kingdom","InvoiceNo":"556531","TotalQuantity":321,"InvoiceValue":765.03,"InvoiceValueExpr":765.03}
{"Country":"United Kingdom","InvoiceNo":"557631","TotalQuantity":178,"InvoiceValue":410.34,"InvoiceValueExpr":410.34}
{"Country":"United Kingdom","InvoiceNo":"C557791","TotalQuantity":-2,"InvoiceValue":-11.2,"InvoiceValueExpr":-11.2}
{"Country":"United Kingdom","InvoiceNo":"C558239","TotalQuantity":-1,"InvoiceValue":-3.25,"InvoiceValueExpr":-3.25}
{"Country":"United Kingdom","InvoiceNo":"559123","TotalQuantity":188,"InvoiceValue":253.26,"InvoiceValueExpr":253.26}
{"Country":"United Kingdom","InvoiceNo":"560826","TotalQuantity":418,"InvoiceValue":512.94,"InvoiceValueExpr":512.94}
{"Country":"United Kingdom","InvoiceNo":"560924","TotalQuantity":472,"InvoiceValue":647.92,"InvoiceValueExpr":647.92}
{"Country":"United Kingdom","InvoiceNo":"562113","TotalQuantity":424,"InvoiceValue":1674.5,"InvoiceValueExpr":1674.5}
{"Country":"United Kingdom","InvoiceNo":"C562124","TotalQuantity":-35,"InvoiceValue":-39.7,"InvoiceValueExpr":-39.7}
{"Country":"United Kingdom","InvoiceNo":"562140","TotalQuantity":43,"InvoiceValue":95.85,"InvoiceValueExpr":95.85}
{"Country":"Spain","InvoiceNo":"562287","TotalQuantity":33,"InvoiceValue":78.56,"InvoiceValueExpr":78.56}
{"Country":"United Kingdom","InvoiceNo":"562389","TotalQuantity":214,"InvoiceValue":199.7,"InvoiceValueExpr":199.7}
{"Country":"United Kingdom","InvoiceNo":"562420","TotalQuantity":523,"InvoiceValue":1691.32,"InvoiceValueExpr":1691.32}
{"Country":"United Kingdom","InvoiceNo":"562587","TotalQuantity":844,"InvoiceValue":1444.66,"InvoiceValueExpr":1444.66}
{"Country":"United Kingdom","InvoiceNo":"562968","TotalQuantity":222,"InvoiceValue":325.32,"InvoiceValueExpr":325.32}
{"Country":"Switzerland","InvoiceNo":"C563224","TotalQuantity":-1,"InvoiceValue":-4.95,"InvoiceValueExpr":-4.95}
{"Country":"United Kingdom","InvoiceNo":"564046","TotalQuantity":400,"InvoiceValue":1020.0,"InvoiceValueExpr":1020.0}
{"Country":"United Kingdom","InvoiceNo":"564198","TotalQuantity":148,"InvoiceValue":150.44,"InvoiceValueExpr":150.44}
{"Country":"United Kingdom","InvoiceNo":"564540","TotalQuantity":11,"InvoiceValue":38.41,"InvoiceValueExpr":38.41}
{"Country":"United Kingdom","InvoiceNo":"564736","TotalQuantity":204,"InvoiceValue":505.8,"InvoiceValueExpr":505.8}
{"Country":"United Kingdom","InvoiceNo":"564742","TotalQuantity":92,"InvoiceValue":154.02,"InvoiceValueExpr":154.02}
{"Country":"United Kingdom","InvoiceNo":"C564900","TotalQuantity":-3,"InvoiceValue":-11.25,"InvoiceValueExpr":-11.25}
{"Country":"United Kingdom","InvoiceNo":"565733","TotalQuantity":80,"InvoiceValue":164.4,"InvoiceValueExpr":164.4}
{"Country":"United Kingdom","InvoiceNo":"565807","TotalQuantity":170,"InvoiceValue":315.2,"InvoiceValueExpr":315.2}
{"Country":"United Kingdom","InvoiceNo":"566403","TotalQuantity":114,"InvoiceValue":501.9,"InvoiceValueExpr":501.9}
{"Country":"United Kingdom","InvoiceNo":"566558","TotalQuantity":361,"InvoiceValue":679.69,"InvoiceValueExpr":679.69}
{"Country":"United Kingdom","InvoiceNo":"566580","TotalQuantity":424,"InvoiceValue":690.9,"InvoiceValueExpr":690.9}
{"Country":"United Kingdom","InvoiceNo":"566591","TotalQuantity":589,"InvoiceValue":570.19,"InvoiceValueExpr":570.19}
{"Country":"United Kingdom","InvoiceNo":"C566671","TotalQuantity":-5,"InvoiceValue":-23.22,"InvoiceValueExpr":-23.22}
{"Country":"France","InvoiceNo":"566873","TotalQuantity":164,"InvoiceValue":240.28,"InvoiceValueExpr":240.28}
{"Country":"United Kingdom","InvoiceNo":"567701","TotalQuantity":480,"InvoiceValue":317.76,"InvoiceValueExpr":317.76}
{"Country":"United Kingdom","InvoiceNo":"567888","TotalQuantity":24,"InvoiceValue":118.8,"InvoiceValueExpr":118.8}
{"Country":"United Kingdom","InvoiceNo":"568158","TotalQuantity":511,"InvoiceValue":1146.8,"InvoiceValueExpr":1146.8}
{"Country":"United Kingdom","InvoiceNo":"568314","TotalQuantity":222,"InvoiceValue":488.98,"InvoiceValueExpr":488.98}
{"Country":"France","InvoiceNo":"568994","TotalQuantity":288,"InvoiceValue":361.76,"InvoiceValueExpr":361.76}
{"Country":"United Kingdom","InvoiceNo":"569202","TotalQuantity":523,"InvoiceValue":1818.09,"InvoiceValueExpr":1818.09}
{"Country":"United Kingdom","InvoiceNo":"569895","TotalQuantity":420,"InvoiceValue":0.0,"InvoiceValueExpr":0.0}
{"Country":"United Kingdom","InvoiceNo":"569935","TotalQuantity":1,"InvoiceValue":0.0,"InvoiceValueExpr":0.0}
{"Country":"United Kingdom","InvoiceNo":"C569984","TotalQuantity":-1,"InvoiceValue":-7.95,"InvoiceValueExpr":-7.95}
{"Country":"United Kingdom","InvoiceNo":"570121","TotalQuantity":275,"InvoiceValue":221.06,"InvoiceValueExpr":221.06}
{"Country":"United Kingdom","InvoiceNo":"570488","TotalQuantity":779,"InvoiceValue":3380.86,"InvoiceValueExpr":3380.86}
{"Country":"United Kingdom","InvoiceNo":"570642","TotalQuantity":127,"InvoiceValue":73.66,"InvoiceValueExpr":73.66}
{"Country":"United Kingdom","InvoiceNo":"570676","TotalQuantity":107,"InvoiceValue":306.07,"InvoiceValueExpr":306.07}
{"Country":"United Kingdom","InvoiceNo":"570807","TotalQuantity":168,"InvoiceValue":397.29,"InvoiceValueExpr":397.29}
{"Country":"Italy","InvoiceNo":"570919","TotalQuantity":60,"InvoiceValue":318.06,"InvoiceValueExpr":318.06}
{"Country":"United Kingdom","InvoiceNo":"571060","TotalQuantity":1,"InvoiceValue":2.49,"InvoiceValueExpr":2.49}
{"Country":"United Kingdom","InvoiceNo":"571179","TotalQuantity":1,"InvoiceValue":40.0,"InvoiceValueExpr":40.0}
{"Country":"United Kingdom","InvoiceNo":"571744","TotalQuantity":72,"InvoiceValue":169.2,"InvoiceValueExpr":169.2}
{"Country":"United Kingdom","InvoiceNo":"572196","TotalQuantity":2782,"InvoiceValue":7398.54,"InvoiceValueExpr":7398.54}
{"Country":"United Kingdom","InvoiceNo":"572225","TotalQuantity":651,"InvoiceValue":868.02,"InvoiceValueExpr":868.02}
{"Country":"Germany","InvoiceNo":"572241","TotalQuantity":69,"InvoiceValue":250.4,"InvoiceValueExpr":250.4}
{"Country":"United Kingdom","InvoiceNo":"C572554","TotalQuantity":-36,"InvoiceValue":-38.16,"InvoiceValueExpr":-38.16}
{"Country":"United Kingdom","InvoiceNo":"573886","TotalQuantity":394,"InvoiceValue":312.82,"InvoiceValueExpr":312.82}
{"Country":"United Kingdom","InvoiceNo":"574353","TotalQuantity":145,"InvoiceValue":312.55,"InvoiceValueExpr":312.55}
{"Country":"United Kingdom","InvoiceNo":"574685","TotalQuantity":86,"InvoiceValue":174.9,"InvoiceValueExpr":174.9}
{"Country":"Spain","InvoiceNo":"574838","TotalQuantity":5,"InvoiceValue":140.0,"InvoiceValueExpr":140.0}
{"Country":"United Kingdom","InvoiceNo":"574881","TotalQuantity":63,"InvoiceValue":115.23,"InvoiceValueExpr":115.23}
{"Country":"Germany","InvoiceNo":"574885","TotalQuantity":137,"InvoiceValue":268.08,"InvoiceValueExpr":268.08}
{"Country":"United Kingdom","InvoiceNo":"575200","TotalQuantity":6,"InvoiceValue":12.48,"InvoiceValueExpr":12.48}
{"Country":"United Kingdom","InvoiceNo":"575924","TotalQuantity":89,"InvoiceValue":149.23,"InvoiceValueExpr":149.23}
{"Country":"United Kingdom","InvoiceNo":"576070","TotalQuantity":385,"InvoiceValue":512.76,"InvoiceValueExpr":512.76}
{"Country":"United Kingdom","InvoiceNo":"576772","TotalQuantity":170,"InvoiceValue":434.5,"InvoiceValueExpr":434.5}
{"Country":"United Kingdom","InvoiceNo":"578095","TotalQuantity":-9,"InvoiceValue":0.0,"InvoiceValueExpr":0.0}
{"Country":"United Kingdom","InvoiceNo":"578117","TotalQuantity":134,"InvoiceValue":223.5,"InvoiceValueExpr":223.5}
{"Country":"United Kingdom","InvoiceNo":"C578363","TotalQuantity":-948,"InvoiceValue":-2210.64,"InvoiceValueExpr":-2210.64}
{"Country":"United Kingdom","InvoiceNo":"578826","TotalQuantity":75,"InvoiceValue":279.75,"InvoiceValueExpr":279.75}
{"Country":"United Kingdom","InvoiceNo":"578935","TotalQuantity":142,"InvoiceValue":316.14,"InvoiceValueExpr":316.14}
{"Country":"United Kingdom","InvoiceNo":"579003","TotalQuantity":166,"InvoiceValue":231.95,"InvoiceValueExpr":231.95}
{"Country":"United Kingdom","InvoiceNo":"579619","TotalQuantity":70,"InvoiceValue":117.54,"InvoiceValueExpr":117.54}
{"Country":"United Kingdom","InvoiceNo":"580044","TotalQuantity":195,"InvoiceValue":334.39,"InvoiceValueExpr":334.39}
{"Country":"United Kingdom","InvoiceNo":"580848","TotalQuantity":44,"InvoiceValue":109.75,"InvoiceValueExpr":109.75}
