{"Country":"United Kingdom","InvoiceNo":"536674","TotalQuantity":122,"InvoiceValue":127.08,"InvoiceValueExpr":127.08}
{"Country":"United Kingdom","InvoiceNo":"536987","TotalQuantity":124,"InvoiceValue":272.01,"InvoiceValueExpr":272.01}
{"Country":"United Kingdom","InvoiceNo":"537643","TotalQuantity":269,"InvoiceValue":2416.59,"InvoiceValueExpr":2416.59}
{"Country":"United Kingdom","InvoiceNo":"C537832","TotalQuantity":-8,"InvoiceValue":-29.8,"InvoiceValueExpr":-29.8}
{"Country":"United Kingdom","InvoiceNo":"538068","TotalQuantity":499,"InvoiceValue":300.92,"InvoiceValueExpr":300.92}
{"Country":"United Kingdom","InvoiceNo":"538343","TotalQuantity":170,"InvoiceValue":385.58,"InvoiceValueExpr":385.58}
{"Country":"United Kingdom","InvoiceNo":"538659","TotalQuantity":255,"InvoiceValue":585.53,"InvoiceValueExpr":585.53}
{"Country":"Portugal","InvoiceNo":"C538889","TotalQuantity":-3,"InvoiceValue":-14.85,"InvoiceValueExpr":-14.85}
{"Country":"United Kingdom","InvoiceNo":"539283","TotalQuantity":95,"InvoiceValue":250.65,"InvoiceValueExpr":250.65}
{"Country":"United Kingdom","InvoiceNo":"539760","TotalQuantity":250,"InvoiceValue":424.17,"InvoiceValueExpr":424.17}
{"Country":"France","InvoiceNo":"540239","TotalQuantity":373,"InvoiceValue":835.11,"InvoiceValueExpr":835.11}
{"Country":"United Kingdom","InvoiceNo":"C540394","TotalQuantity":-1,"InvoiceValue":-4.95,"InvoiceValueExpr":-4.95}
{"Country":"United Kingdom","InvoiceNo":"540565","TotalQuantity":40,"InvoiceValue":102.0,"InvoiceValueExpr":102.0}
{"Country":"United Kingdom","InvoiceNo":"540680","TotalQuantity":365,"InvoiceValue":434.04,"InvoiceValueExpr":434.04}
{"Country":"United Kingdom","InvoiceNo":"540943","TotalQuantity":107,"InvoiceValue":220.33,"InvoiceValueExpr":220.33}
{"Country":"United Kingdom","InvoiceNo":"C541234","TotalQuantity":-3,"InvoiceValue":-9.6,"InvoiceValueExpr":-9.6}
{"Country":"United Kingdom","InvoiceNo":"C541499","TotalQuantity":-5,"InvoiceValue":-22.05,"InvoiceValueExpr":-22.05}
{"Country":"United Kingdom","InvoiceNo":"C541828","TotalQuantity":-3,"InvoiceValue":-3.8,"InvoiceValueExpr":-3.8}
{"Country":"United Kingdom","InvoiceNo":"541846","TotalQuantity":191,"InvoiceValue":323.09,"InvoiceValueExpr":323.09}
{"Country":"United Kingdom","InvoiceNo":"542112","TotalQuantity":365,"InvoiceValue":632.18,"InvoiceValueExpr":632.18}
{"Country":"United Kingdom","InvoiceNo":"543451","TotalQuantity":87,"InvoiceValue":605.97,"InvoiceValueExpr":605.97}
{"Country":"United Kingdom","InvoiceNo":"543542","TotalQuantity":256,"InvoiceValue":231.91,"InvoiceValueExpr":231.91}
{"Country":"United Kingdom","InvoiceNo":"C543756","TotalQuantity":-24,"InvoiceValue":-54.6,"InvoiceValueExpr":-54.6}
{"Country":"United Kingdom","InvoiceNo":"544398","TotalQuantity":321,"InvoiceValue":518.2,"InvoiceValueExpr":518.2}
{"Country":"EIRE","InvoiceNo":"546263","TotalQuantity":218,"InvoiceValue":461.6,"InvoiceValueExpr":461.6}
{"Country":"United Kingdom","InvoiceNo":"546863","TotalQuantity":1500,"InvoiceValue":676.2,"InvoiceValueExpr":676.2}
{"Country":"United Kingdom","InvoiceNo":"546884","TotalQuantity":372,"InvoiceValue":1546.93,"InvoiceValueExpr":1546.93}
{"Country":"United Kingdom","InvoiceNo":"C546931","TotalQuantity":-2,"InvoiceValue":-4.2,"InvoiceValueExpr":-4.2}
{"Country":"United Kingdom","InvoiceNo":"547367","TotalQuantity":79,"InvoiceValue":200.16,"InvoiceValueExpr":200.16}
{"Country":"United Kingdom","InvoiceNo":"548507","TotalQuantity":10,"InvoiceValue":31.77,"InvoiceValueExpr":31.77}
{"Country":"United Kingdom","InvoiceNo":"548548","TotalQuantity":8,"InvoiceValue":102.0,"InvoiceValueExpr":102.0}
{"Country":"United Kingdom","InvoiceNo":"C548625","TotalQuantity":-2,"InvoiceValue":-11.9,"InvoiceValueExpr":-11.9}
{"Country":"United Kingdom","InvoiceNo":"550457","TotalQuantity":750,"InvoiceValue":1231.6,"InvoiceValueExpr":1231.6}
{"Country":"United Kingdom","InvoiceNo":"550523","TotalQuantity":145,"InvoiceValue":267.91,"InvoiceValueExpr":267.91}
{"Country":"United Kingdom","InvoiceNo":"550667","TotalQuantity":5040,"InvoiceValue":2016.0,"InvoiceValueExpr":2016.0}
{"Country":"United Kingdom","InvoiceNo":"C550752","TotalQuantity":-1,"InvoiceValue":-3.75,"InvoiceValueExpr":-3.75}
{"Country":"United Kingdom","InvoiceNo":"C550810","TotalQuantity":-2,"InvoiceValue":-11.9,"InvoiceValueExpr":-11.9}
{"Country":"United Kingdom","InvoiceNo":"551197","TotalQuantity":68,"InvoiceValue":166.4,"InvoiceValueExpr":166.4}
{"Country":"United Kingdom","InvoiceNo":"551320","TotalQuantity":60,"InvoiceValue":0.0,"InvoiceValueExpr":0.0}
{"Country":"United Kingdom","InvoiceNo":"551390","TotalQuantity":150,"InvoiceValue":259.45,"InvoiceValueExpr":259.45}
{"Country":"United Kingdom","InvoiceNo":"C551551","TotalQuantity":-9,"InvoiceValue":-20.27,"InvoiceValueExpr":-20.27}
{"Country":"United Kingdom","InvoiceNo":"552017","TotalQuantity":11,"InvoiceValue":26.42,"InvoiceValueExpr":26.42}
{"Country":"Spain","InvoiceNo":"552040","TotalQuantity":88,"InvoiceValue":522.6,"InvoiceValueExpr":522.6}
{"Country":"United Kingdom","InvoiceNo":"552181","TotalQuantity":820,"InvoiceValue":1484.4,"InvoiceValueExpr":1484.4}
{"Country":"United Kingdom","InvoiceNo":"552554","TotalQuantity":152,"InvoiceValue":319.51,"InvoiceValueExpr":319.51}
{"Country":"United Kingdom","InvoiceNo":"552715","TotalQuantity":146,"InvoiceValue":305.26,"InvoiceValueExpr":305.26}
{"Country":"United Kingdom","InvoiceNo":"552868","TotalQuantity":12,"InvoiceValue":5.04,"InvoiceValueExpr":5.04}
{"Country":"United Kingdom","InvoiceNo":"553197","TotalQuantity":36,"InvoiceValue":63.44,"InvoiceValueExpr":63.44}
{"Country":"Germany","InvoiceNo":"553884","TotalQuantity":47,"InvoiceValue":202.26,"InvoiceValueExpr":202.26}
{"Country":"Italy","InvoiceNo":"555107","TotalQuantity":267,"InvoiceValue":587.45,"InvoiceValueExpr":587.45}
{"Country":"United Kingdom","InvoiceNo":"C555860","TotalQuantity":-1,"InvoiceValue":-16.95,"InvoiceValueExpr":-16.95}
{"Country":"United Kingdom","InvoiceNo":"557145","TotalQuantity":459,"InvoiceValue":802.13,"InvoiceValueExpr":802.13}
{"Country":"United Kingdom","InvoiceNo":"557855","TotalQuantity":69,"InvoiceValue":127.19,"InvoiceValueExpr":127.19}
{"Country":"United Kingdom","InvoiceNo":"C557927","TotalQuantity":-1,"InvoiceValue":-10.0,"InvoiceValueExpr":-10.0}
{"Country":"United Kingdom","InvoiceNo":"C557946","TotalQuantity":-13,"InvoiceValue":-25.05,"InvoiceValueExpr":-25.05}
{"Country":"United Kingdom","InvoiceNo":"557966","TotalQuantity":128,"InvoiceValue":607.2,"InvoiceValueExpr":607.2}
{"Country":"United Kingdom","InvoiceNo":"C559012","TotalQuantity":-10,"InvoiceValue":-27.98,"InvoiceValueExpr":-27.98}
{"Country":"United Kingdom","InvoiceNo":"559668","TotalQuantity":406,"InvoiceValue":301.26,"InvoiceValueExpr":301.26}
{"Country":"United Kingdom","InvoiceNo":"C559983","TotalQuantity":-130,"InvoiceValue":-261.3,"InvoiceValueExpr":-261.3}
{"Country":"United Kingdom","InvoiceNo":"560034","TotalQuantity":113,"InvoiceValue":300.99,"InvoiceValueExpr":300.99}
{"Country":"United Kingdom","InvoiceNo":"560538","TotalQuantity":192,"InvoiceValue":306.4,"InvoiceValueExpr":306.4}
{"Country":"United Kingdom","InvoiceNo":"560580","TotalQuantity":2565,"InvoiceValue":8801.51,"InvoiceValueExpr":8801.51}
{"Country":"United Kingdom","InvoiceNo":"560887","TotalQuantity":944,"InvoiceValue":2064.8,"InvoiceValueExpr":2064.8}
{"Country":"United Kingdom","InvoiceNo":"561036","TotalQuantity":160,"InvoiceValue":301.39,"InvoiceValueExpr":301.39}
{"Country":"United Kingdom","InvoiceNo":"561091","TotalQuantity":70,"InvoiceValue":217.44,"InvoiceValueExpr":217.44}
{"Country":"United Kingdom","InvoiceNo":"561611","TotalQuantity":89,"InvoiceValue":249.38,"InvoiceValueExpr":249.38}
{"Country":"United Kingdom","InvoiceNo":"561750","TotalQuantity":158,"InvoiceValue":308.71,"InvoiceValueExpr":308.71}
{"Country":"United Kingdom","InvoiceNo":"562550","TotalQuantity":24,"InvoiceValue":90.0,"InvoiceValueExpr":90.0}
{"Country":"United Kingdom","InvoiceNo":"C562808","TotalQuantity":-5,"InvoiceValue":-1.45,"InvoiceValueExpr":-1.45}
{"Country":"United Kingdom","InvoiceNo":"545289","TotalQuantity":242,"InvoiceValue":470.88,"InvoiceValueExpr":470.88}
{"Country":"United Kingdom","InvoiceNo":"555946","TotalQuantity":77,"InvoiceValue":184.59,"InvoiceValueExpr":184.59}
{"Country":"United Kingdom","InvoiceNo":"561205","TotalQuantity":231,"InvoiceValue":200.47,"InvoiceValueExpr":200.47}
{"Country":"United Kingdom","InvoiceNo":"C562953","TotalQuantity":-7,"InvoiceValue":-18.35,"InvoiceValueExpr":-18.35}
{"Country":"United Kingdom","InvoiceNo":"563543","TotalQuantity":273,"InvoiceValue":685.61,"InvoiceValueExpr":685.61}
{"Country":"United Kingdom","InvoiceNo":"563552","TotalQuantity":71,"InvoiceValue":267.15,"InvoiceValueExpr":267.15}
{"Country":"United Kingdom","InvoiceNo":"563707","TotalQuantity":50,"InvoiceValue":137.3,"InvoiceValueExpr":137.3}
{"Country":"United Kingdom","InvoiceNo":"563733","TotalQuantity":339,"InvoiceValue":574.31,"InvoiceValueExpr":574.31}
{"Country":"United Kingdom","InvoiceNo":"563736","TotalQuantity":88,"InvoiceValue":336.24,"InvoiceValueExpr":336.24}
{"Country":"United Kingdom","InvoiceNo":"564164","TotalQuantity":300,"InvoiceValue":75.0,"InvoiceValueExpr":75.0}
{"Country":"United Kingdom","InvoiceNo":"565725","TotalQuantity":542,"InvoiceValue":537.9,"InvoiceValueExpr":537.9}
{"Country":"United Kingdom","InvoiceNo":"565914","TotalQuantity":180,"InvoiceValue":89.64,"InvoiceValueExpr":89.64}
{"Country":"United Kingdom","InvoiceNo":"566396","TotalQuantity":268,"InvoiceValue":553.74,"InvoiceValueExpr":553.74}
{"Country":"United Kingdom","InvoiceNo":"566967","TotalQuantity":177,"InvoiceValue":397.17,"InvoiceValueExpr":397.17}
{"Country":"United Kingdom","InvoiceNo":"C567350","TotalQuantity":-4,"InvoiceValue":-16.6,"InvoiceValueExpr":-16.6}
{"Country":"United Kingdom","InvoiceNo":"567374","TotalQuantity":812,"InvoiceValue":2020.52,"InvoiceValueExpr":2020.52}
{"Country":"United Kingdom","InvoiceNo":"C567527","TotalQuantity":-756,"InvoiceValue":-3825.36,"InvoiceValueExpr":-3825.36}
{"Country":"United Kingdom","InvoiceNo":"567808","TotalQuantity":4,"InvoiceValue":12.4,"InvoiceValueExpr":12.4}
{"Country":"United Kingdom","InvoiceNo":"567875","TotalQuantity":171,"InvoiceValue":275.4,"InvoiceValueExpr":275.4}
{"Country":"United Kingdom","InvoiceNo":"568044","TotalQuantity":187,"InvoiceValue":522.49,"InvoiceValueExpr":522.49}
{"Country":"United Kingdom","InvoiceNo":"568101","TotalQuantity":888,"InvoiceValue":1098.78,"InvoiceValueExpr":1098.78}
{"Country":"United Kingdom","InvoiceNo":"568185","TotalQuantity":64,"InvoiceValue":181.09,"InvoiceValueExpr":181.09}
{"Country":"United Kingdom","InvoiceNo":"568592","TotalQuantity":172,"InvoiceValue":441.8,"InvoiceValueExpr":441.8}
{"Country":"United Kingdom","InvoiceNo":"C568911","TotalQuantity":-36,"InvoiceValue":-15.12,"InvoiceValueExpr":-15.12}
{"Country":"United Kingdom","InvoiceNo":"C569116","TotalQuantity":-12,"InvoiceValue":-15.0,"InvoiceValueExpr":-15.0}
{"Country":"United Kingdom","InvoiceNo":"569389","TotalQuantity":3,"InvoiceValue":305.0,"InvoiceValueExpr":305.0}
{"Country":"United Kingdom","InvoiceNo":"569694","TotalQuantity":263,"InvoiceValue":562.47,"InvoiceValueExpr":562.47}
{"Country":"United Kingdom","InvoiceNo":"569839","TotalQuantity":1300,"InvoiceValue":2327.0,"InvoiceValueExpr":2327.0}
{"Country":"United Kingdom","InvoiceNo":"571260","TotalQuantity":69,"InvoiceValue":127.2,"InvoiceValueExpr":127.2}
{"Country":"United Kingdom","InvoiceNo":"C571501","TotalQuantity":-1,"InvoiceValue":-153.13,"InvoiceValueExpr":-153.13}
{"Country":"United Kingdom","InvoiceNo":"571511","TotalQuantity":160,"InvoiceValue":240.68,"InvoiceValueExpr":240.68}
{"Country":"United Kingdom","InvoiceNo":"571909","TotalQuantity":302,"InvoiceValue":502.09,"InvoiceValueExpr":502.09}
{"Country":"United Kingdom","InvoiceNo":"572190","TotalQuantity":4,"InvoiceValue":7.46,"InvoiceValueExpr":7.46}
{"Country":"United Kingdom","InvoiceNo":"572652","TotalQuantity":743,"InvoiceValue":1062.43,"InvoiceValueExpr":1062.43}
{"Country":"United Kingdom","InvoiceNo":"572969","TotalQuantity":443,"InvoiceValue":603.82,"InvoiceValueExpr":603.82}
{"Country":"United Kingdom","InvoiceNo":"573415","TotalQuantity":290,"InvoiceValue":678.01,"InvoiceValueExpr":678.01}
{"Country":"United Kingdom","InvoiceNo":"573888","TotalQuantity":433,"InvoiceValue":370.12,"InvoiceValueExpr":370.12}
{"Country":"United Kingdom","InvoiceNo":"C574003","TotalQuantity":-6,"InvoiceValue":-29.7,"InvoiceValueExpr":-29.7}
{"Country":"United Kingdom","InvoiceNo":"574084","TotalQuantity":278,"InvoiceValue":364.22,"InvoiceValueExpr":364.22}
{"Country":"United Kingdom","InvoiceNo":"574323","TotalQuantity":59,"InvoiceValue":114.91,"InvoiceValueExpr":114.91}
{"Country":"United Kingdom","InvoiceNo":"574445","TotalQuantity":393,"InvoiceValue":713.76,"InvoiceValueExpr":713.76}
{"Country":"Channel Islands","InvoiceNo":"574587","TotalQuantity":616,"InvoiceValue":1228.24,"InvoiceValueExpr":1228.24}
{"Country":"Channel Islands","InvoiceNo":"574588","TotalQuantity":22,"InvoiceValue":74.9,"InvoiceValueExpr":74.9}
{"Country":"United Kingdom","InvoiceNo":"574831","TotalQuantity":257,"InvoiceValue":138.94,"InvoiceValueExpr":138.94}
{"Country":"United Kingdom","InvoiceNo":"575853","TotalQuantity":31,"InvoiceValue":156.43,"InvoiceValueExpr":156.43}
{"Country":"United Kingdom","InvoiceNo":"575944","TotalQuantity":348,"InvoiceValue":524.9,"InvoiceValueExpr":524.9}
{"Country":"United Kingdom","InvoiceNo":"575957","TotalQuantity":147,"InvoiceValue":116.01,"InvoiceValueExpr":116.01}
{"Country":"United Kingdom","InvoiceNo":"C576230","TotalQuantity":-5,"InvoiceValue":-38.45,"InvoiceValueExpr":-38.45}
{"Country":"EIRE","InvoiceNo":"576829","TotalQuantity":34,"InvoiceValue":164.51,"InvoiceValueExpr":164.51}
{"Country":"EIRE","InvoiceNo":"577613","TotalQuantity":614,"InvoiceValue":805.2,"InvoiceValueExpr":805.2}
{"Country":"France","InvoiceNo":"577856","TotalQuantity":186,"InvoiceValue":357.88,"InvoiceValueExpr":357.88}
{"Country":"United Kingdom","InvoiceNo":"578267","TotalQuantity":3,"InvoiceValue":12.75,"InvoiceValueExpr":12.75}
{"Country":"United Kingdom","InvoiceNo":"579435","TotalQuantity":6,"InvoiceValue":43.5,"InvoiceValueExpr":43.5}
{"Country":"United Kingdom","InvoiceNo":"580057","TotalQuantity":250,"InvoiceValue":460.3,"InvoiceValueExpr":460.3}
{"Country":"United Kingdom","InvoiceNo":"580317","TotalQuantity":278,"InvoiceValue":584.52,"InvoiceValueExpr":584.52}
{"Country":"United Kingdom","InvoiceNo":"580615","TotalQuantity":1005,"InvoiceValue":1854.83,"InvoiceValueExpr":1854.83}
{"Country":"United Kingdom","InvoiceNo":"580650","TotalQuantity":458,"InvoiceValue":353.78,"InvoiceValueExpr":353.78}
{"Country":"United Kingdom","InvoiceNo":"580874","TotalQuantity":234,"InvoiceValue":557.44,"InvoiceValueExpr":557.44}
