{"Country":"United Kingdom","InvoiceNo":"C536826","TotalQuantity":-5,"InvoiceValue":-23.25,"InvoiceValueExpr":-23.25}
{"Country":"United Kingdom","InvoiceNo":"537220","TotalQuantity":1,"InvoiceValue":3.35,"InvoiceValueExpr":3.35}
{"Country":"United Kingdom","InvoiceNo":"537240","TotalQuantity":1811,"InvoiceValue":7660.48,"InvoiceValueExpr":7660.48}
{"Country":"United Kingdom","InvoiceNo":"C537600","TotalQuantity":-1,"InvoiceValue":-1.0,"InvoiceValueExpr":-1.0}
{"Country":"United Kingdom","InvoiceNo":"537620","TotalQuantity":54,"InvoiceValue":97.8,"InvoiceValueExpr":97.8}
{"Country":"United Kingdom","InvoiceNo":"537816","TotalQuantity":29,"InvoiceValue":129.75,"InvoiceValueExpr":129.75}
{"Country":"United Kingdom","InvoiceNo":"538288","TotalQuantity":2,"InvoiceValue":1.9,"InvoiceValueExpr":1.9}
{"Country":"France","InvoiceNo":"539435","TotalQuantity":65,"InvoiceValue":180.0,"InvoiceValueExpr":180.0}
{"Country":"United Kingdom","InvoiceNo":"540166","TotalQuantity":400,"InvoiceValue":660.0,"InvoiceValueExpr":660.0}
{"Country":"United Kingdom","InvoiceNo":"541564","TotalQuantity":133,"InvoiceValue":192.26,"InvoiceValueExpr":192.26}
{"Country":"Germany","InvoiceNo":"C542101","TotalQuantity":-10,"InvoiceValue":-44.7,"InvoiceValueExpr":-44.7}
{"Country":"United Kingdom","InvoiceNo":"543034","TotalQuantity":-130,"InvoiceValue":0.0,"InvoiceValueExpr":0.0}
{"Country":"United Kingdom","InvoiceNo":"543186","TotalQuantity":36,"InvoiceValue":196.2,"InvoiceValueExpr":196.2}
{"Country":"United Kingdom","InvoiceNo":"543367","TotalQuantity":269,"InvoiceValue":438.82,"InvoiceValueExpr":438.82}
{"Country":"United Kingdom","InvoiceNo":"543774","TotalQuantity":730,"InvoiceValue":1078.9,"InvoiceValueExpr":1078.9}
{"Country":"United Kingdom","InvoiceNo":"546171","TotalQuantity":90,"InvoiceValue":130.56,"InvoiceValueExpr":130.56}
{"Country":"United Kingdom","InvoiceNo":"546762","TotalQuantity":22,"InvoiceValue":28.18,"InvoiceValueExpr":28.18}
{"Country":"United Kingdom","InvoiceNo":"546873","TotalQuantity":252,"InvoiceValue":326.04,"InvoiceValueExpr":326.04}
{"Country":"United Kingdom","InvoiceNo":"547003","TotalQuantity":25,"InvoiceValue":118.75,"InvoiceValueExpr":118.75}
{"Country":"United Kingdom","InvoiceNo":"C547228","TotalQuantity":-1,"InvoiceValue":-2.1,"InvoiceValueExpr":-2.1}
{"Country":"United Kingdom","InvoiceNo":"547816","TotalQuantity":9,"InvoiceValue":25.25,"InvoiceValueExpr":25.25}
{"Country":"United Kingdom","InvoiceNo":"547886","TotalQuantity":178,"InvoiceValue":329.44,"InvoiceValueExpr":329.44}
{"Country":"United Kingdom","InvoiceNo":"547933","TotalQuantity":1,"InvoiceValue":0.0,"InvoiceValueExpr":0.0}
{"Country":"United Kingdom","InvoiceNo":"548308","TotalQuantity":204,"InvoiceValue":417.75,"InvoiceValueExpr":417.75}
{"Country":"United Kingdom","InvoiceNo":"C548532","TotalQuantity":-216,"InvoiceValue":-1170.0,"InvoiceValueExpr":-1170.0}
{"Country":"United Kingdom","InvoiceNo":"548652","TotalQuantity":108,"InvoiceValue":135.0,"InvoiceValueExpr":135.0}
{"Country":"United Kingdom","InvoiceNo":"548686","TotalQuantity":553,"InvoiceValue":785.5,"InvoiceValueExpr":785.5}
{"Country":"United Kingdom","InvoiceNo":"549300","TotalQuantity":391,"InvoiceValue":768.83,"InvoiceValueExpr":768.83}
{"Country":"United Kingdom","InvoiceNo":"C549986","TotalQuantity":-2,"InvoiceValue":-7.5,"InvoiceValueExpr":-7.5}
{"Country":"United Kingdom","InvoiceNo":"550153","TotalQuantity":-1,"InvoiceValue":0.0,"InvoiceValueExpr":0.0}
{"Country":"United Kingdom","InvoiceNo":"550474","TotalQuantity":502,"InvoiceValue":1625.27,"InvoiceValueExpr":1625.27}
{"Country":"United Kingdom","InvoiceNo":"550616","TotalQuantity":270,"InvoiceValue":354.78,"InvoiceValueExpr":354.78}
{"Country":"United Kingdom","InvoiceNo":"550714","TotalQuantity":320,"InvoiceValue":478.2,"InvoiceValueExpr":478.2}
{"Country":"United Kingdom","InvoiceNo":"550927","TotalQuantity":1,"InvoiceValue":0.0,"InvoiceValueExpr":0.0}
{"Country":"United Kingdom","InvoiceNo":"551033","TotalQuantity":146,"InvoiceValue":354.26,"InvoiceValueExpr":354.26}
{"Country":"United Kingdom","InvoiceNo":"551146","TotalQuantity":20,"InvoiceValue":59.0,"InvoiceValueExpr":59.0}
{"Country":"United Kingdom","InvoiceNo":"551284","TotalQuantity":163,"InvoiceValue":253.94,"InvoiceValueExpr":253.94}
{"Country":"United Kingdom","InvoiceNo":"551435","TotalQuantity":-5,"InvoiceValue":0.0,"InvoiceValueExpr":0.0}
{"Country":"France","InvoiceNo":"553195","TotalQuantity":141,"InvoiceValue":151.4,"InvoiceValueExpr":151.4}
{"Country":"United Kingdom","InvoiceNo":"553940","TotalQuantity":250,"InvoiceValue":419.8,"InvoiceValueExpr":419.8}
{"Country":"United Kingdom","InvoiceNo":"554003","TotalQuantity":256,"InvoiceValue":504.0,"InvoiceValueExpr":504.0}
{"Country":"United Kingdom","InvoiceNo":"554320","TotalQuantity":-102,"InvoiceValue":0.0,"InvoiceValueExpr":0.0}
{"Country":"United Kingdom","InvoiceNo":"555526","TotalQuantity":352,"InvoiceValue":645.3,"InvoiceValueExpr":645.3}
{"Country":"United Kingdom","InvoiceNo":"555703","TotalQuantity":291,"InvoiceValue":309.38,"InvoiceValueExpr":309.38}
{"Country":"United Kingdom","InvoiceNo":"556121","TotalQuantity":68,"InvoiceValue":132.18,"InvoiceValueExpr":132.18}
{"Country":"United Kingdom","InvoiceNo":"556685","TotalQuantity":381,"InvoiceValue":597.07,"InvoiceValueExpr":597.07}
{"Country":"United Kingdom","InvoiceNo":"556727","TotalQuantity":234,"InvoiceValue":555.8,"InvoiceValueExpr":555.8}
{"Country":"United Kingdom","InvoiceNo":"557217","TotalQuantity":1259,"InvoiceValue":1987.19,"InvoiceValueExpr":1987.19}
{"Country":"United Kingdom","InvoiceNo":"557227","TotalQuantity":4,"InvoiceValue":23.0,"InvoiceValueExpr":23.0}
{"Country":"United Kingdom","InvoiceNo":"C557638","TotalQuantity":-1,"InvoiceValue":-545.58,"InvoiceValueExpr":-545.58}
{"Country":"United Kingdom","InvoiceNo":"557967","TotalQuantity":168,"InvoiceValue":497.9,"InvoiceValueExpr":497.9}
{"Country":"United Kingdom","InvoiceNo":"C558716","TotalQuantity":-349,"InvoiceValue":-128.27,"InvoiceValueExpr":-128.27}
{"Country":"United Kingdom","InvoiceNo":"558914","TotalQuantity":11,"InvoiceValue":0.0,"InvoiceValueExpr":0.0}
{"Country":"United Kingdom","InvoiceNo":"559639","TotalQuantity":180,"InvoiceValue":457.26,"InvoiceValueExpr":457.26}
{"Country":"United Kingdom","InvoiceNo":"560047","TotalQuantity":135,"InvoiceValue":221.73,"InvoiceValueExpr":221.73}
{"Country":"France","InvoiceNo":"560272","TotalQuantity":47,"InvoiceValue":150.1,"InvoiceValueExpr":150.1}
{"Country":"United Kingdom","InvoiceNo":"561034","TotalQuantity":146,"InvoiceValue":209.35,"InvoiceValueExpr":209.35}
{"Country":"Switzerland","InvoiceNo":"C561117","TotalQuantity":-3,"InvoiceValue":-120.0,"InvoiceValueExpr":-120.0}
{"Country":"United Kingdom","InvoiceNo":"561128","TotalQuantity":197,"InvoiceValue":331.74,"InvoiceValueExpr":331.74}
{"Country":"United Kingdom","InvoiceNo":"561243","TotalQuantity":19,"InvoiceValue":36.68,"InvoiceValueExpr":36.68}
{"Country":"United Kingdom","InvoiceNo":"561396","TotalQuantity":512,"InvoiceValue":794.58,"InvoiceValueExpr":794.58}
{"Country":"United Kingdom","InvoiceNo":"561465","TotalQuantity":223,"InvoiceValue":259.01,"InvoiceValueExpr":259.01}
{"Country":"United Kingdom","InvoiceNo":"562050","TotalQuantity":24,"InvoiceValue":19.92,"InvoiceValueExpr":19.92}
{"Country":"United Kingdom","InvoiceNo":"562838","TotalQuantity":317,"InvoiceValue":382.85,"InvoiceValueExpr":382.85}
{"Country":"United Kingdom","InvoiceNo":"545287","TotalQuantity":60,"InvoiceValue":117.0,"InvoiceValueExpr":117.0}
{"Country":"United Kingdom","InvoiceNo":"553833","TotalQuantity":139,"InvoiceValue":222.31,"InvoiceValueExpr":222.31}
{"Country":"United Kingdom","InvoiceNo":"558332","TotalQuantity":8,"InvoiceValue":59.6,"InvoiceValueExpr":59.6}
{"Country":"United Kingdom","InvoiceNo":"558921","TotalQuantity":10,"InvoiceValue":20.8,"InvoiceValueExpr":20.8}
{"Country":"Germany","InvoiceNo":"564328","TotalQuantity":178,"InvoiceValue":383.92,"InvoiceValueExpr":383.92}
{"Country":"United Kingdom","InvoiceNo":"565045","TotalQuantity":-115,"InvoiceValue":0.0,"InvoiceValueExpr":0.0}
{"Country":"Germany","InvoiceNo":"565442","TotalQuantity":559,"InvoiceValue":819.26,"InvoiceValueExpr":819.26}
{"Country":"France","InvoiceNo":"566256","TotalQuantity":43,"InvoiceValue":112.38,"InvoiceValueExpr":112.38}
{"Country":"United Kingdom","InvoiceNo":"566297","TotalQuantity":58,"InvoiceValue":92.38,"InvoiceValueExpr":92.38}
{"Country":"United Kingdom","InvoiceNo":"566446","TotalQuantity":501,"InvoiceValue":1748.93,"InvoiceValueExpr":1748.93}
{"Country":"United Kingdom","InvoiceNo":"567183","TotalQuantity":2748,"InvoiceValue":3844.84,"InvoiceValueExpr":3844.84}
{"Country":"United Kingdom","InvoiceNo":"567636","TotalQuantity":298,"InvoiceValue":672.4,"InvoiceValueExpr":672.4}
{"Country":"United Kingdom","InvoiceNo":"567674","TotalQuantity":2,"InvoiceValue":1.7,"InvoiceValueExpr":1.7}
{"Country":"United Kingdom","InvoiceNo":"568342","TotalQuantity":78,"InvoiceValue":149.34,"InvoiceValueExpr":149.34}
{"Country":"United Kingdom","InvoiceNo":"568513","TotalQuantity":471,"InvoiceValue":865.53,"InvoiceValueExpr":865.53}
{"Country":"United Kingdom","InvoiceNo":"568868","TotalQuantity":441,"InvoiceValue":872.23,"InvoiceValueExpr":872.23}
{"Country":"United Kingdom","InvoiceNo":"569225","TotalQuantity":185,"InvoiceValue":195.31,"InvoiceValueExpr":195.31}
{"Country":"United Kingdom","InvoiceNo":"569380","TotalQuantity":-140,"InvoiceValue":0.0,"InvoiceValueExpr":0.0}
{"Country":"Belgium","InvoiceNo":"569496","TotalQuantity":118,"InvoiceValue":346.68,"InvoiceValueExpr":346.68}
{"Country":"United Kingdom","InvoiceNo":"569530","TotalQuantity":287,"InvoiceValue":111.68,"InvoiceValueExpr":111.68}
{"Country":"United Kingdom","InvoiceNo":"569643","TotalQuantity":200,"InvoiceValue":343.66,"InvoiceValueExpr":343.66}
{"Country":"United Kingdom","InvoiceNo":"C569829","TotalQuantity":-2,"InvoiceValue":-32.81,"InvoiceValueExpr":-32.81}
{"Country":"United Kingdom","InvoiceNo":"570238","TotalQuantity":49,"InvoiceValue":129.93,"InvoiceValueExpr":129.93}
{"Country":"United Kingdom","InvoiceNo":"570270","TotalQuantity":18,"InvoiceValue":111.9,"InvoiceValueExpr":111.9}
{"Country":"United Kingdom","InvoiceNo":"570505","TotalQuantity":263,"InvoiceValue":379.79,"InvoiceValueExpr":379.79}
{"Country":"France","InvoiceNo":"570724","TotalQuantity":162,"InvoiceValue":153.12,"InvoiceValueExpr":153.12}
{"Country":"United Kingdom","InvoiceNo":"571100","TotalQuantity":108,"InvoiceValue":106.92,"InvoiceValueExpr":106.92}
{"Country":"United Kingdom","InvoiceNo":"572301","TotalQuantity":56,"InvoiceValue":111.81,"InvoiceValueExpr":111.81}
{"Country":"United Kingdom","InvoiceNo":"572480","TotalQuantity":-100,"InvoiceValue":0.0,"InvoiceValueExpr":0.0}
{"Country":"United Kingdom","InvoiceNo":"573169","TotalQuantity":1,"InvoiceValue":0.0,"InvoiceValueExpr":0.0}
{"Country":"United Kingdom","InvoiceNo":"573576","TotalQuantity":1265,"InvoiceValue":4941.71,"InvoiceValueExpr":4941.71}
{"Country":"United Kingdom","InvoiceNo":"573917","TotalQuantity":48,"InvoiceValue":147.0,"InvoiceValueExpr":147.0}
{"Country":"Poland","InvoiceNo":"574343","TotalQuantity":302,"InvoiceValue":379.28,"InvoiceValueExpr":379.28}
{"Country":"United Kingdom","InvoiceNo":"575188","TotalQuantity":120,"InvoiceValue":310.9,"InvoiceValueExpr":310.9}
{"Country":"United Kingdom","InvoiceNo":"575387","TotalQuantity":64,"InvoiceValue":76.8,"InvoiceValueExpr":76.8}
{"Country":"United Kingdom","InvoiceNo":"575576","TotalQuantity":338,"InvoiceValue":439.66,"InvoiceValueExpr":439.66}
{"Country":"United Kingdom","InvoiceNo":"575643","TotalQuantity":184,"InvoiceValue":384.88,"InvoiceValueExpr":384.88}
{"Country":"United Kingdom","InvoiceNo":"575676","TotalQuantity":578,"InvoiceValue":323.62,"InvoiceValueExpr":323.62}
{"Country":"United Kingdom","InvoiceNo":"576063","TotalQuantity":115,"InvoiceValue":330.45,"InvoiceValueExpr":330.45}
{"Country":"United Kingdom","InvoiceNo":"576842","TotalQuantity":226,"InvoiceValue":295.8,"InvoiceValueExpr":295.8}
{"Country":"United Kingdom","InvoiceNo":"577000","TotalQuantity":120,"InvoiceValue":306.0,"InvoiceValueExpr":306.0}
{"Country":"United Kingdom","InvoiceNo":"577358","TotalQuantity":1621,"InvoiceValue":5957.66,"InvoiceValueExpr":5957.66}
{"Country":"United Kingdom","InvoiceNo":"577410","TotalQuantity":164,"InvoiceValue":248.85,"InvoiceValueExpr":248.85}
{"Country":"United Kingdom","InvoiceNo":"577527","TotalQuantity":97,"InvoiceValue":188.73,"InvoiceValueExpr":188.73}
{"Country":"United Kingdom","InvoiceNo":"577596","TotalQuantity":312,"InvoiceValue":390.0,"InvoiceValueExpr":390.0}
{"Country":"United Kingdom","InvoiceNo":"577742","TotalQuantity":224,"InvoiceValue":456.12,"InvoiceValueExpr":456.12}
{"Country":"United Kingdom","InvoiceNo":"577748","TotalQuantity":828,"InvoiceValue":1437.5,"InvoiceValueExpr":1437.5}
{"Country":"United Kingdom","InvoiceNo":"578149","TotalQuantity":1008,"InvoiceValue":8124.25,"InvoiceValueExpr":8124.25}
{"Country":"United Kingdom","InvoiceNo":"C578148","TotalQuantity":-1,"InvoiceValue":-1.65,"InvoiceValueExpr":-1.65}
{"Country":"United Kingdom","InvoiceNo":"578857","TotalQuantity":22,"InvoiceValue":38.2,"InvoiceValueExpr":38.2}
{"Country":"United Kingdom","InvoiceNo":"578946","TotalQuantity":71,"InvoiceValue":145.83,"InvoiceValueExpr":145.83}
{"Country":"United Kingdom","InvoiceNo":"579459","TotalQuantity":99,"InvoiceValue":321.9,"InvoiceValueExpr":321.9}
{"Country":"United Kingdom","InvoiceNo":"579507","TotalQuantity":120,"InvoiceValue":261.68,"InvoiceValueExpr":261.68}
{"Country":"United Kingdom","InvoiceNo":"579837","TotalQuantity":140,"InvoiceValue":991.2,"InvoiceValueExpr":991.2}
{"Country":"United Kingdom","InvoiceNo":"580278","TotalQuantity":64,"InvoiceValue":174.37,"InvoiceValueExpr":174.37}
{"Country":"United Kingdom","InvoiceNo":"581008","TotalQuantity":156,"InvoiceValue":361.8,"InvoiceValueExpr":361.8}
{"Country":"United Kingdom","InvoiceNo":"581236","TotalQuantity":186,"InvoiceValue":124.54,"InvoiceValueExpr":124.54}
{"Country":"United Kingdom","InvoiceNo":"581448","TotalQuantity":48,"InvoiceValue":207.6,"InvoiceValueExpr":207.6}
{"Country":"United Kingdom","InvoiceNo":"581501","TotalQuantity":692,"InvoiceValue":485.0,"InvoiceValueExpr":485.0}
{"Country":"United Kingdom","InvoiceNo":"576846","TotalQuantity":289,"InvoiceValue":497.97,"InvoiceValueExpr":497.97}
